{"query": "fragment WebhookFragment on Webhook {\n  id\n  name\n  isActive\n  app {\n    id\n    name\n    __typename\n  }\n  __typename\n}\n\nfragment WebhooksDetailsFragment on Webhook {\n  ...WebhookFragment\n  __typename\n}\n\nfragment WebhookErrorFragment on WebhookError {\n  code\n  field\n  __typename\n}\n\nmutation WebhookCreate($input: WebhookCreateInput!) {\n  webhookCreate(input: $input) {\n    errors: webhookErrors {\n      ...WebhookErrorFragment\n      __typename\n    }\n    webhook {\n      ...WebhooksDetailsFragment\n      __typename\n    }\n    __typename\n  }\n}\n", "variables": {"input": {"app": "QXBwOjI=", "events": ["ANY_EVENTS"], "isActive": true, "name": "SuperHook", "secretKey": "123", "targetUrl": "http://localhost:9001/"}}, "operationName": "WebhookCreate"}